AUTHORS.txt
LICENSE
MANIFEST.in
README.rst
setup.py
djrill/__init__.py
djrill/_version.py
djrill/admin.py
djrill/compat.py
djrill/exceptions.py
djrill/forms.py
djrill/models.py
djrill/signals.py
djrill/urls.py
djrill/views.py
djrill.egg-info/PKG-INFO
djrill.egg-info/SOURCES.txt
djrill.egg-info/dependency_links.txt
djrill.egg-info/not-zip-safe
djrill.egg-info/requires.txt
djrill.egg-info/top_level.txt
djrill/mail/__init__.py
djrill/mail/backends/__init__.py
djrill/mail/backends/djrill.py
djrill/templates/djrill/_status.html
djrill/templates/djrill/index.html
djrill/templates/djrill/senders_list.html
djrill/templates/djrill/status.html
djrill/templates/djrill/tags_list.html
djrill/templates/djrill/urls_list.html
djrill/templatetags/__init__.py
djrill/templatetags/djrill_future.py