Metadata-Version: 1.1
Name: djrill
Version: 1.3.0
Summary: Mandrill transactional email for Django
Home-page: https://github.com/brack3t/Djrill/
Author: Kenneth Love <kenneth@brack3t.com>, Chris Jones <chris@brack3t.com>
Author-email: kenneth@brack3t.com
License: BSD License
Keywords: django,mailchimp,mandrill,email,email backend
Platform: UNKNOWN
Classifier: Programming Language :: Python
Classifier: Programming Language :: Python :: Implementation :: PyPy
Classifier: Programming Language :: Python :: Implementation :: CPython
Classifier: Programming Language :: Python :: 2.6
Classifier: Programming Language :: Python :: 2.7
Classifier: Programming Language :: Python :: 3
Classifier: Programming Language :: Python :: 3.2
Classifier: Programming Language :: Python :: 3.3
Classifier: Programming Language :: Python :: 3.4
Classifier: License :: OSI Approved :: BSD License
Classifier: Topic :: Software Development :: Libraries :: Python Modules
Classifier: Framework :: Django
Classifier: Environment :: Web Environment
